MANIFEST.in
README.rst
requirements.txt
setup.cfg
setup.py
kotti_controlpanel/__init__.py
kotti_controlpanel/__init__.pyc
kotti_controlpanel/config.py
kotti_controlpanel/config.pyc
kotti_controlpanel/events.py
kotti_controlpanel/events.pyc
kotti_controlpanel/fanstatic.py
kotti_controlpanel/fanstatic.pyc
kotti_controlpanel/forms.py
kotti_controlpanel/forms.pyc
kotti_controlpanel/resources.py
kotti_controlpanel/resources.pyc
kotti_controlpanel/util.py
kotti_controlpanel/util.pyc
kotti_controlpanel.egg-info/PKG-INFO
kotti_controlpanel.egg-info/SOURCES.txt
kotti_controlpanel.egg-info/dependency_links.txt
kotti_controlpanel.egg-info/entry_points.txt
kotti_controlpanel.egg-info/not-zip-safe
kotti_controlpanel.egg-info/requires.txt
kotti_controlpanel.egg-info/top_level.txt
kotti_controlpanel/alembic/README
kotti_controlpanel/alembic/env.py
kotti_controlpanel/alembic/env.pyc
kotti_controlpanel/alembic/script.py.mako
kotti_controlpanel/alembic/versions/.gitkeep
kotti_controlpanel/alembic/versions/README.md
kotti_controlpanel/locale/.gitkeep
kotti_controlpanel/locale/README
kotti_controlpanel/static/gears.png
kotti_controlpanel/static/scripts.js
kotti_controlpanel/static/scripts.min.js
kotti_controlpanel/static/styles.css
kotti_controlpanel/static/styles.min.css
kotti_controlpanel/templates/add_option.pt
kotti_controlpanel/templates/controlpanel-dump.pt
kotti_controlpanel/templates/controlpanel.pt
kotti_controlpanel/templates/cpanel.pt
kotti_controlpanel/templates/options.pt
kotti_controlpanel/templates/settings.pt
kotti_controlpanel/templates/view.pt
kotti_controlpanel/tests/conftest.py
kotti_controlpanel/tests/test_functional.py
kotti_controlpanel/tests/test_resources.py
kotti_controlpanel/tests/test_view.py
kotti_controlpanel/views/__init__.py
kotti_controlpanel/views/__init__.pyc
kotti_controlpanel/views/edit.pyc
kotti_controlpanel/views/view.py
kotti_controlpanel/views/view.pyc