Metadata-Version: 1.1
Name: kotti-controlpanel
Version: 1.0.9
Summary: Settings configuration for Kotti
Home-page: https://github.com/b4oshany/kotti_controlpanel
Author: Oshane Bailey
Author-email: b4.oshany@gmail.com
License: BSD-derived (http://www.repoze.org/LICENSE.txt)
Keywords: ui settings controlpanel kotti web cms wcms pylons pyramid sqlalchemy bootstrap
Platform: UNKNOWN
Classifier: Programming Language :: Python
Classifier: Programming Language :: Python :: 2.7
Classifier: Framework :: Pylons
Classifier: Topic :: Internet :: WWW/HTTP
Classifier: Topic :: Internet :: WWW/HTTP :: Dynamic Content
Classifier: Topic :: Internet :: WWW/HTTP :: WSGI :: Application
Classifier: License :: Repoze Public License
